{
    "switch": [
        {
            "Porta": 18,
            "Conexao": "CORE01",
            "Descricao": "ISL PORT",
            "DIO": "TX3/RX3",
            "Velocidade ( Giga )": 10
        },
        {
            "Porta": 2,
            "Conexao": "AGG_CMN",
            "Descricao": "Trunk",
            "DIO": "TWINAX",
            "Velocidade ( Giga )": 10
        },
        {
            "Porta": 17,
            "Conexao": "IPQ",
            "Descricao": "ISLPORT",
            "DIO": "RX4/TX4",
            "Velocidade ( Giga )": 10
        },
        {
            "Porta": 19,
            "Conexao": "INRAD",
            "Descricao": "ISLPORT",
            "DIO": "PAR 29",
            "Velocidade ( Giga )": 10
        },
        {
            "Porta": 33,
            "Conexao": "PABX",
            "Descricao": "ISLPORT",
            "DIO": "DIO01 PAR01-03 RX1/TX1",
            "Velocidade ( Giga )": 10
        }
    ]
}